{
  "ID": "621ee8be-960d-4489-b984-2e7b5045aca8",
  "Version": "2.3.3.0",
  "Name": "TWGameBackGroundLayer",
  "Content": {
    "Content": {
      "Animation": {
        "Duration": 0,
        "Speed": 1.0,
        "Timelines": [],
        "ctype": "TimelineActionData"
      },
      "AnimationList": [],
      "ObjectData": {
        "Children": [
          {
            "FileData": {
              "Type": "Normal",
              "Path": "twgamebg.jpg",
              "Plist": ""
            },
            "Scale9Width": 1280,
            "Scale9Height": 720,
            "AnchorPoint": {
              "ScaleX": 0.5,
              "ScaleY": 0.5
            },
            "Position": {
              "X": 640.0,
              "Y": 360.0
            },
            "Scale": {
              "ScaleX": 1.0,
              "ScaleY": 1.0
            },
            "CColor": {},
            "IconVisible": false,
            "PrePosition": {
              "X": 0.5,
              "Y": 0.5
            },
            "PreSize": {
              "X": 1.0,
              "Y": 1.0
            },
            "Tag": 2,
            "ActionTag": 1425388959,
            "Size": {
              "X": 1280.0,
              "Y": 720.0
            },
            "Name": "Image_1",
            "ctype": "ImageViewObjectData"
          }
        ],
        "Size": {
          "X": 1280.0,
          "Y": 720.0
        },
        "Name": "Layer",
        "ctype": "LayerObjectData"
      },
      "UsedResources": [
        "twgamebg.jpg"
      ],
      "ctype": "GameFileData"
    }
  },
  "Type": "Layer"
}